Lab1/vending_machine/change_state.v
`include "vending_machine_def.v"


module change_state(clk,reset_n,current_total_nxt,current_total);

	input clk;
	input reset_n;
	input [`kTotalBits-1:0] current_total_nxt;
	output reg [`kTotalBits-1:0] current_total;
	
	// Sequential circuit to reset or update the states
	always @(posedge clk) begin
		if (!reset_n) begin
			// TODO: reset all states.
			current_total = 0;
		end
		else begin
			// TODO: update all states.
			current_total = current_total_nxt;
		end
	end
endmodule

Lab1/vending_machine/calculate_current_state.v

`include "vending_machine_def.v"
	

module calculate_current_state(i_input_coin,i_select_item,item_price,coin_value,current_total,
input_total,current_total_nxt,o_available_item,o_output_item);


	
	input [`kNumCoins-1:0] i_input_coin;
	input [`kNumItems-1:0]	i_select_item;			
	input [31:0] item_price [`kNumItems-1:0];
	input [31:0] coin_value [`kNumCoins-1:0];	
	input [`kTotalBits-1:0] current_total;
	output reg [`kNumItems-1:0] o_available_item,o_output_item;
	output reg  [`kTotalBits-1:0] input_total, current_total_nxt;
	integer i;
	
	// Combinational logic for the next states
	always @(*) begin
		// TODO: current_total_nxt
        input_total = 0;
        for (i = 0; i < `kNumCoins; i = i + 1) begin
            if (i_input_coin[i])
                input_total = input_total + coin_value[i];
        end
		current_total_nxt = current_total + input_total;
		
        for (i = 0; i < `kNumItems; i = i + 1) begin
			if(o_output_item[i] == 1)
				current_total_nxt  = current_total_nxt - item_price[i];
        end
    end
	
	
	// Combinational logic for the outputs
	always @(*) begin
		// TODO: o_available_item
		// TODO: o_output_item
		o_available_item = 4'b0000;
		o_output_item = 4'b0000;
        for (i = 0; i < `kNumItems; i = i + 1) begin
            if (item_price[i] <= current_total)
				o_available_item[i] = 1;
				if(i_select_item[i] == 1)
					o_output_item[i] = 1;
        end
	end
endmodule

Lab1/vending_machine/check_time_and_coin.v
`include "vending_machine_def.v"

	

module check_time_and_coin(i_input_coin,i_select_item,i_trigger_return,clk,current_total,coin_value,reset_n,wait_time,o_return_coin);
	input clk;
	input [`kTotalBits-1:0] current_total;
	input [31:0] coin_value [`kNumCoins-1:0];	
	input reset_n;
	input [`kNumCoins-1:0] i_input_coin;
	input [`kNumItems-1:0]	i_select_item;
	input i_trigger_return;
	output reg  [`kNumCoins-1:0] o_return_coin;
	output reg [31:0] wait_time;
	reg is_reset;

	// initiate values
	initial begin
        wait_time = `kWaitTime;
        o_return_coin = 3'b000;
		is_reset = 0;
	end
	
	// update coin return time
	always @(i_input_coin, i_select_item) begin
		is_reset = 0;
		if(i_input_coin != 0)
			is_reset = 1;
	end

	always @(*) begin
		o_return_coin = 3'b000;
		if (wait_time == 0 || i_trigger_return  == 1) begin
			if (current_total >= (coin_value[2] + coin_value[1] + coin_value[0])) 
				o_return_coin = 3'b111;
			else if (current_total >= (coin_value[2] + coin_value[1])) 
				o_return_coin = 3'b110;
			else if (current_total >= (coin_value[2] + coin_value[0])) 
				o_return_coin = 3'b101;			
			else if (current_total >= coin_value[2]) 
				o_return_coin = 3'b100;			
			else if (current_total >= (coin_value[1] + coin_value[0])) 
				o_return_coin = 3'b011;			
			else if (current_total >= (coin_value[1])) 
				o_return_coin = 3'b010;			
			else if (current_total >= (coin_value[0])) 
				o_return_coin = 3'b001;
			else
				o_return_coin = 3'b000;
		end
	end
	
	always @(posedge clk) begin
		if (!reset_n || is_reset == 1) begin
		// TODO: reset all states.
			wait_time = `kWaitTime;
		end
		else begin
		// TODO: update all states.
			wait_time = wait_time - 1;
		end
	end
endmodule

Lab1/vending_machine/vending_machine.v
// Title         : vending_machine.v
// Author      : Jae-Eon Jo (Jojaeeon@postech.ac.kr) 
//			     Dongup Kwon (nankdu7@postech.ac.kr) (2015.03.30)
//			     Jaehun Ryu (jaehunryu@postech.ac.kr) (2021.03.07)

`include "vending_machine_def.v"


module vending_machine (
	clk,							// Clock signal
	reset_n,						// Reset signal (active-low)

	i_input_coin,				// coin is inserted.
	i_select_item,				// item is selected.
	i_trigger_return,			// change-return is triggered 

	o_available_item,			// Sign of the item availability
	o_output_item,			// Sign of the item withdrawal
	o_return_coin				// Sign of the coin return
);

	// Ports Declaration
	// Do not modify the module interface
	input clk;
	input reset_n;
	
	input [`kNumCoins-1:0] i_input_coin;
	input [`kNumItems-1:0] i_select_item;
	input i_trigger_return;
		
	output [`kNumItems-1:0] o_available_item;
	output [`kNumItems-1:0] o_output_item;
	output [`kNumCoins-1:0] o_return_coin;


	

	// Do not modify the values.
	wire [31:0] item_price [`kNumItems-1:0];	// Price of each item
	wire [31:0] coin_value [`kNumCoins-1:0];	// Value of each coin
	assign item_price[0] = 400;
	assign item_price[1] = 500;
	assign item_price[2] = 1000;
	assign item_price[3] = 2000;
	assign coin_value[0] = 100;
	assign coin_value[1] = 500;
	assign coin_value[2] = 1000;

	// Internal states. You may add your own net variables.
	wire [`kTotalBits-1:0] current_total;
	
	// Next internal states. You may add your own net variables.
	wire [`kTotalBits-1:0] current_total_nxt;

	
	// Variables. You may add more your own net variables.
	wire [`kTotalBits-1:0] input_total;
	wire [31:0] wait_time;


	// This module interface, structure, and given a number of modules are not mandatory but recommended.
	// However, Implementations that use modules are mandatory.
		
  	check_time_and_coin check_time_and_coin_module(.i_input_coin(i_input_coin),
  									.i_select_item(i_select_item),
									.i_trigger_return(i_trigger_return),
									.clk(clk),
									.current_total(current_total),
									.coin_value(coin_value),
									.reset_n(reset_n),
									.wait_time(wait_time),
									.o_return_coin(o_return_coin));

	calculate_current_state calculate_current_state_module(.i_input_coin(i_input_coin),
										.i_select_item(i_select_item),
										.item_price(item_price),
										.coin_value(coin_value),
										.current_total(current_total),
										.input_total(input_total),
										.current_total_nxt(current_total_nxt),
										.o_available_item(o_available_item),
										.o_output_item(o_output_item));
	
  	change_state change_state_module(
						.clk(clk),
						.reset_n(reset_n),
						.current_total_nxt(current_total_nxt),
						.current_total(current_total));


endmodule

Lab1/vending_machine/waveform.vcd
$version Generated by VerilatedVcd $end
$timescale 1ps $end
 $scope module TOP $end
  $var wire 1 + clk $end
  $var wire 1 , reset_n $end
  $var wire 3 - i_input_coin [2:0] $end
  $var wire 4 . i_select_item [3:0] $end
  $var wire 1 / i_trigger_return $end
  $var wire 4 0 o_available_item [3:0] $end
  $var wire 4 1 o_output_item [3:0] $end
  $var wire 3 2 o_return_coin [2:0] $end
  $scope module vending_machine $end
   $var wire 1 + clk $end
   $var wire 1 , reset_n $end
   $var wire 3 - i_input_coin [2:0] $end
   $var wire 4 . i_select_item [3:0] $end
   $var wire 1 / i_trigger_return $end
   $var wire 4 0 o_available_item [3:0] $end
   $var wire 4 1 o_output_item [3:0] $end
   $var wire 3 2 o_return_coin [2:0] $end
   $var wire 32 # item_price[0] [31:0] $end
   $var wire 32 $ item_price[1] [31:0] $end
   $var wire 32 % item_price[2] [31:0] $end
   $var wire 32 & item_price[3] [31:0] $end
   $var wire 32 ' coin_value[0] [31:0] $end
   $var wire 32 ( coin_value[1] [31:0] $end
   $var wire 32 ) coin_value[2] [31:0] $end
   $var wire 31 3 current_total [30:0] $end
   $var wire 31 4 current_total_nxt [30:0] $end
   $var wire 31 5 input_total [30:0] $end
   $var wire 32 6 wait_time [31:0] $end
   $scope module calculate_current_state_module $end
    $var wire 3 - i_input_coin [2:0] $end
    $var wire 4 . i_select_item [3:0] $end
    $var wire 32 # item_price[0] [31:0] $end
    $var wire 32 $ item_price[1] [31:0] $end
    $var wire 32 % item_price[2] [31:0] $end
    $var wire 32 & item_price[3] [31:0] $end
    $var wire 32 ' coin_value[0] [31:0] $end
    $var wire 32 ( coin_value[1] [31:0] $end
    $var wire 32 ) coin_value[2] [31:0] $end
    $var wire 31 3 current_total [30:0] $end
    $var wire 4 0 o_available_item [3:0] $end
    $var wire 4 1 o_output_item [3:0] $end
    $var wire 31 5 input_total [30:0] $end
    $var wire 31 4 current_total_nxt [30:0] $end
    $var wire 32 * i [31:0] $end
   $upscope $end
   $scope module change_state_module $end
    $var wire 1 + clk $end
    $var wire 1 , reset_n $end
    $var wire 31 4 current_total_nxt [30:0] $end
    $var wire 31 3 current_total [30:0] $end
   $upscope $end
   $scope module check_time_and_coin_module $end
    $var wire 1 + clk $end
    $var wire 31 3 current_total [30:0] $end
    $var wire 32 ' coin_value[0] [31:0] $end
    $var wire 32 ( coin_value[1] [31:0] $end
    $var wire 32 ) coin_value[2] [31:0] $end
    $var wire 1 , reset_n $end
    $var wire 3 - i_input_coin [2:0] $end
    $var wire 4 . i_select_item [3:0] $end
    $var wire 1 / i_trigger_return $end
    $var wire 3 2 o_return_coin [2:0] $end
    $var wire 32 6 wait_time [31:0] $end
    $var wire 1 7 is_reset $end
   $upscope $end
  $upscope $end
 $upscope $end
$enddefinitions $end


#0
b00000000000000000000000110010000 #
b00000000000000000000000111110100 $
b00000000000000000000001111101000 %
b00000000000000000000011111010000 &
b00000000000000000000000001100100 '
b00000000000000000000000111110100 (
b00000000000000000000001111101000 )
b00000000000000000000000000000100 *
1+
0,
b010 -
b0100 .
0/
b1111 0
b0100 1
b000 2
b1110011010110000001011000110101 3
b1110011010110000001010001000001 4
b0000000000000000000000111110100 5
b00000000000000000000000001100100 6
17
#1
0+
1,
#2
1+
0,
b0000 0
b0000000000000000000000000000000 3
b1111111111111111111111000001100 4
#3
0+
#4
1+
1,
b000 -
b0000 .
b0000 1
b0000000000000000000000000000000 4
b0000000000000000000000000000000 5
b00000000000000000000000001100011 6
07
#5
0+
#6
1+
b00000000000000000000000001100010 6
#7
0+
#8
1+
b00000000000000000000000001100001 6
#9
0+
#10
1+
b001 -
b0000000000000000000000001100100 3
b0000000000000000000000011001000 4
b0000000000000000000000001100100 5
b00000000000000000000000001100100 6
17
#11
0+
b000 -
b0000000000000000000000001100100 4
b0000000000000000000000000000000 5
07
#12
1+
b001 -
b0000000000000000000000011001000 3
b0000000000000000000000100101100 4
b0000000000000000000000001100100 5
17
#13
0+
b000 -
b0000000000000000000000011001000 4
b0000000000000000000000000000000 5
07
#14
1+
b001 -
b0000000000000000000000100101100 3
b0000000000000000000000110010000 4
b0000000000000000000000001100100 5
17
#15
0+
b000 -
b0000000000000000000000100101100 4
b0000000000000000000000000000000 5
07
#16
1+
b001 -
b0001 0
b0000000000000000000000110010000 3
b0000000000000000000000111110100 4
b0000000000000000000000001100100 5
17
#17
0+
b000 -
b0000000000000000000000110010000 4
b0000000000000000000000000000000 5
07
#18
1+
b001 -
b0011 0
b0000000000000000000000111110100 3
b0000000000000000000001001011000 4
b0000000000000000000000001100100 5
17
#19
0+
b000 -
b0000000000000000000000111110100 4
b0000000000000000000000000000000 5
07
#20
1+
b001 -
b0000000000000000000001001011000 3
b0000000000000000000001010111100 4
b0000000000000000000000001100100 5
17
#21
0+
b000 -
b0000000000000000000001001011000 4
b0000000000000000000000000000000 5
07
#22
1+
b001 -
b0000000000000000000001010111100 3
b0000000000000000000001100100000 4
b0000000000000000000000001100100 5
17
#23
0+
b000 -
b0000000000000000000001010111100 4
b0000000000000000000000000000000 5
07
#24
1+
b001 -
b0000000000000000000001100100000 3
b0000000000000000000001110000100 4
b0000000000000000000000001100100 5
17
#25
0+
b000 -
b0000000000000000000001100100000 4
b0000000000000000000000000000000 5
07
#26
1+
b001 -
b0000000000000000000001110000100 3
b0000000000000000000001111101000 4
b0000000000000000000000001100100 5
17
#27
0+
b000 -
b0000000000000000000001110000100 4
b0000000000000000000000000000000 5
07
#28
1+
b001 -
b0111 0
b0000000000000000000001111101000 3
b0000000000000000000010001001100 4
b0000000000000000000000001100100 5
17
#29
0+
b000 -
b0000000000000000000001111101000 4
b0000000000000000000000000000000 5
07
#30
1+
b001 -
b0000000000000000000010001001100 3
b0000000000000000000010010110000 4
b0000000000000000000000001100100 5
17
#31
0+
b000 -
b0000000000000000000010001001100 4
b0000000000000000000000000000000 5
07
#32
1+
b001 -
b0000000000000000000010010110000 3
b0000000000000000000010100010100 4
b0000000000000000000000001100100 5
17
#33
0+
b000 -
b0000000000000000000010010110000 4
b0000000000000000000000000000000 5
07
#34
1+
b001 -
b0000000000000000000010100010100 3
b0000000000000000000010101111000 4
b0000000000000000000000001100100 5
17
#35
0+
b000 -
b0000000000000000000010100010100 4
b0000000000000000000000000000000 5
07
#36
1+
b001 -
b0000000000000000000010101111000 3
b0000000000000000000010111011100 4
b0000000000000000000000001100100 5
17
#37
0+
b000 -
b0000000000000000000010101111000 4
b0000000000000000000000000000000 5
07
#38
1+
b001 -
b0000000000000000000010111011100 3
b0000000000000000000011001000000 4
b0000000000000000000000001100100 5
17
#39
0+
b000 -
b0000000000000000000010111011100 4
b0000000000000000000000000000000 5
07
#40
1+
b001 -
b0000000000000000000011001000000 3
b0000000000000000000011010100100 4
b0000000000000000000000001100100 5
17
#41
0+
b000 -
b0000000000000000000011001000000 4
b0000000000000000000000000000000 5
07
#42
1+
b001 -
b0000000000000000000011010100100 3
b0000000000000000000011100001000 4
b0000000000000000000000001100100 5
17
#43
0+
b000 -
b0000000000000000000011010100100 4
b0000000000000000000000000000000 5
07
#44
1+
b001 -
b0000000000000000000011100001000 3
b0000000000000000000011101101100 4
b0000000000000000000000001100100 5
17
#45
0+
b000 -
b0000000000000000000011100001000 4
b0000000000000000000000000000000 5
07
#46
1+
b001 -
b0000000000000000000011101101100 3
b0000000000000000000011111010000 4
b0000000000000000000000001100100 5
17
#47
0+
b000 -
b0000000000000000000011101101100 4
b0000000000000000000000000000000 5
07
#48
1+
b001 -
b1111 0
b0000000000000000000011111010000 3
b0000000000000000000100000110100 4
b0000000000000000000000001100100 5
17
#49
0+
b000 -
b0000000000000000000011111010000 4
b0000000000000000000000000000000 5
07
#50
1+
b00000000000000000000000001100011 6
#51
0+
#52
1+
0,
b0000 0
b0000000000000000000000000000000 3
b0000000000000000000000000000000 4
b00000000000000000000000001100100 6
#53
0+
1,
b001 -
b0000000000000000000000001100100 4
b0000000000000000000000001100100 5
17
#54
1+
b0000000000000000000000001100100 3
b0000000000000000000000011001000 4
#55
0+
b000 -
1/
b001 2
b0000000000000000000000001100100 4
b0000000000000000000000000000000 5
07
#56
1+
b00000000000000000000000001100011 6
#57
0+
#58
1+
b00000000000000000000000001100010 6
#59
0+
#60
1+
b00000000000000000000000001100001 6
#61
0+
0/
b000 2
#62
1+
0,
b0000000000000000000000000000000 3
b0000000000000000000000000000000 4
b00000000000000000000000001100100 6
#63
0+
1,
b010 -
b0000000000000000000000111110100 4
b0000000000000000000000111110100 5
17
#64
1+
b0011 0
b0000000000000000000000111110100 3
b0000000000000000000001111101000 4
#65
0+
b000 -
1/
b010 2
b0000000000000000000000111110100 4
b0000000000000000000000000000000 5
07
#66
1+
b00000000000000000000000001100011 6
#67
0+
#68
1+
b00000000000000000000000001100010 6
#69
0+
#70
1+
b00000000000000000000000001100001 6
#71
0+
0/
b000 2
#72
1+
0,
b0000 0
b0000000000000000000000000000000 3
b0000000000000000000000000000000 4
b00000000000000000000000001100100 6
#73
0+
1,
b100 -
b0000000000000000000001111101000 4
b0000000000000000000001111101000 5
17
#74
1+
b0111 0
b0000000000000000000001111101000 3
b0000000000000000000011111010000 4
#75
0+
b000 -
1/
b100 2
b0000000000000000000001111101000 4
b0000000000000000000000000000000 5
07
#76
1+
b00000000000000000000000001100011 6
#77
0+
#78
1+
b00000000000000000000000001100010 6
#79
0+
#80
1+
b00000000000000000000000001100001 6
#81
0+
0/
b000 2
#82
1+
0,
b0000 0
b0000000000000000000000000000000 3
b0000000000000000000000000000000 4
b00000000000000000000000001100100 6
#83
0+
1,
b011 -
b0000000000000000000001001011000 4
b0000000000000000000001001011000 5
17
#84
1+
b0011 0
b0000000000000000000001001011000 3
b0000000000000000000010010110000 4
#85
0+
b000 -
1/
b011 2
b0000000000000000000001001011000 4
b0000000000000000000000000000000 5
07
#86
1+
b00000000000000000000000001100011 6
#87
0+
#88
1+
b00000000000000000000000001100010 6
#89
0+
#90
1+
b00000000000000000000000001100001 6
#91
0+
0/
b000 2
#92
1+
0,
b0000 0
b0000000000000000000000000000000 3
b0000000000000000000000000000000 4
b00000000000000000000000001100100 6
#93
0+
1,
b101 -
b0000000000000000000010001001100 4
b0000000000000000000010001001100 5
17
#94
1+
b0111 0
b0000000000000000000010001001100 3
b0000000000000000000100010011000 4
#95
0+
b000 -
1/
b101 2
b0000000000000000000010001001100 4
b0000000000000000000000000000000 5
07
#96
1+
b00000000000000000000000001100011 6
#97
0+
#98
1+
b00000000000000000000000001100010 6
#99
0+
#100
1+
b00000000000000000000000001100001 6
#101
0+
0/
b000 2
#102
1+
0,
b0000 0
b0000000000000000000000000000000 3
b0000000000000000000000000000000 4
b00000000000000000000000001100100 6
#103
0+
1,
b110 -
b0000000000000000000010111011100 4
b0000000000000000000010111011100 5
17
#104
1+
b0111 0
b0000000000000000000010111011100 3
b0000000000000000000101110111000 4
#105
0+
b000 -
1/
b110 2
b0000000000000000000010111011100 4
b0000000000000000000000000000000 5
07
#106
1+
b00000000000000000000000001100011 6
#107
0+
#108
1+
b00000000000000000000000001100010 6
#109
0+
#110
1+
b00000000000000000000000001100001 6
#111
0+
0/
b000 2
#112
1+
0,
b0000 0
b0000000000000000000000000000000 3
b0000000000000000000000000000000 4
b00000000000000000000000001100100 6
#113
0+
1,
b111 -
b0000000000000000000011001000000 4
b0000000000000000000011001000000 5
17
#114
1+
b0111 0
b0000000000000000000011001000000 3
b0000000000000000000110010000000 4
#115
0+
b000 -
1/
b111 2
b0000000000000000000011001000000 4
b0000000000000000000000000000000 5
07
#116
1+
b00000000000000000000000001100011 6
#117
0+
#118
1+
b00000000000000000000000001100010 6
#119
0+
#120
1+
b00000000000000000000000001100001 6
#121
0+
0/
b000 2
#122
1+
0,
b0000 0
b0000000000000000000000000000000 3
b0000000000000000000000000000000 4
b00000000000000000000000001100100 6
#123
0+
1,
b111 -
b0000000000000000000011001000000 4
b0000000000000000000011001000000 5
17
#124
1+
b0111 0
b0000000000000000000011001000000 3
b0000000000000000000110010000000 4
#125
0+
b000 -
b0000000000000000000011001000000 4
b0000000000000000000000000000000 5
07
#126
1+
b0110 .
b0000 0
b0110 1
b0000000000000000000000001100100 3
b1111111111111111111101010001000 4
b00000000000000000000000001100011 6
#127
0+
b0000 .
b0000 1
b0000000000000000000000001100100 4
#128
1+
b00000000000000000000000001100010 6
#129
0+
#130
1+
b00000000000000000000000001100001 6
#131
0+
#132
1+
b00000000000000000000000001100000 6
#133
0+
#134
1+
b00000000000000000000000001011111 6
#135
0+
#136
1+
b00000000000000000000000001011110 6
#137
0+
#138
1+
b00000000000000000000000001011101 6
#139
0+
#140
1+
b00000000000000000000000001011100 6
#141
0+
#142
1+
b00000000000000000000000001011011 6
#143
0+
#144
1+
b00000000000000000000000001011010 6
#145
0+
#146
1+
b00000000000000000000000001011001 6
#147
0+
#148
1+
b00000000000000000000000001011000 6
#149
0+
#150
1+
b00000000000000000000000001010111 6
#151
0+
#152
1+
b00000000000000000000000001010110 6
#153
0+
#154
1+
b00000000000000000000000001010101 6
#155
0+
#156
1+
b00000000000000000000000001010100 6
#157
0+
#158
1+
b00000000000000000000000001010011 6
#159
0+
#160
1+
b00000000000000000000000001010010 6
#161
0+
#162
1+
b00000000000000000000000001010001 6
#163
0+
#164
1+
b00000000000000000000000001010000 6
#165
0+
#166
1+
b00000000000000000000000001001111 6
#167
0+
#168
1+
b00000000000000000000000001001110 6
#169
0+
#170
1+
b00000000000000000000000001001101 6
#171
0+
#172
1+
b00000000000000000000000001001100 6
#173
0+
#174
1+
b00000000000000000000000001001011 6
#175
0+
#176
1+
b00000000000000000000000001001010 6
#177
0+
#178
1+
b00000000000000000000000001001001 6
#179
0+
#180
1+
b00000000000000000000000001001000 6
#181
0+
#182
1+
b00000000000000000000000001000111 6
#183
0+
#184
1+
b00000000000000000000000001000110 6
#185
0+
#186
1+
b00000000000000000000000001000101 6
#187
0+
#188
1+
b00000000000000000000000001000100 6
#189
0+
#190
1+
b00000000000000000000000001000011 6
#191
0+
#192
1+
b00000000000000000000000001000010 6
#193
0+
#194
1+
b00000000000000000000000001000001 6
#195
0+
#196
1+
b00000000000000000000000001000000 6
#197
0+
#198
1+
b00000000000000000000000000111111 6
